{
  "generatedAt": "2026-07-16T14:06:40+00:00",
  "listingCount": 427,
  "geocodingAccuracy": 0.9977,
  "priceParsingSuccess": 1.0,
  "areaParsingSuccess": 1.0,
  "freshnessWithin30Days": 1.0,
  "duplicateRate": 0.0656,
  "outlierCount": 1,
  "suspiciousPpsfCount": 0,
  "confidenceMedian": 100.0,
  "confidenceBands": {
    "High": 426,
    "Medium": 1,
    "Low": 0
  },
  "ppsfRange": {
    "min": 2000.0,
    "max": 71794.87,
    "median": 14400.0
  },
  "topOutliers": [
    {
      "id": "zameen-54478685",
      "source": "Zameen",
      "title": "10 Kanal Luxury Farmhouse | 4 Bedrooms | 2 Swimming Pools (Indoor & Outdoor) | Spacious Lawn | Scenic Location | Opposite Bahria Enclave",
      "neighborhood": "Bahria Town",
      "pricePerSqft": 4000.0,
      "reasons": [
        "far below comparable median"
      ],
      "url": "https://www.zameen.com/Property/bahria_enclave_bahria_enclave_-_sector_m_10_kanal_luxury_farmhouse_4_bedrooms_2_swimming_pools_indoor_outdoor_spacious_lawn_scenic_location_opposite_bahria_enclave-54478685-11977-1.html"
    }
  ],
  "fbrReference": {
    "label": "FBR Islamabad immovable property valuation",
    "url": "https://www.fbr.gov.pk/propertyValuation/17653",
    "documentUrl": "https://download1.fbr.gov.pk/SROs/2026416174174449SRO644.pdf",
    "note": "Official valuation reference. Numeric matching is shown only when an area table is mapped."
  }
}