{
  "generatedAt": "2026-06-29T15:51:42+00:00",
  "city": "Islamabad",
  "trackedListings": 494,
  "mappedListings": 461,
  "outlierCount": 2,
  "neighborhoodCount": 71,
  "medianPricePkr": 28250000.0,
  "medianPricePerSqft": 15525.72,
  "medianPricePerMarla": 3493285.12,
  "medianFreshnessHours": 5.0,
  "medianConfidenceScore": 100.0,
  "confidenceBands": {
    "High": 461,
    "Medium": 32,
    "Low": 1
  },
  "sourceMix": {
    "Graana": {
      "label": "Graana",
      "count": 61,
      "share": 0.1235
    },
    "Zameen": {
      "label": "Zameen",
      "count": 433,
      "share": 0.8765
    }
  },
  "propertyGroups": [
    {
      "propertyGroup": "house",
      "label": "Houses",
      "listingCount": 192,
      "mappedCount": 166,
      "outlierCount": 0,
      "medianPricePkr": 59500000.0,
      "medianPricePerSqft": 25944.44
    },
    {
      "propertyGroup": "apartment",
      "label": "Flats & Apartments",
      "listingCount": 152,
      "mappedCount": 145,
      "outlierCount": 1,
      "medianPricePkr": 13000000.0,
      "medianPricePerSqft": 13076.92
    },
    {
      "propertyGroup": "plot",
      "label": "Residential Plots",
      "listingCount": 150,
      "mappedCount": 150,
      "outlierCount": 1,
      "medianPricePkr": 23500000.0,
      "medianPricePerSqft": 7222.22
    }
  ],
  "topNeighborhoods": [
    {
      "neighborhood": "New Blue Area",
      "listingCount": 2,
      "mappedCount": 2,
      "outlierCount": 0,
      "medianPricePkr": 145000000.0,
      "medianPricePerSqft": 63591.73,
      "medianPricePerMarla": 14308139.54
    },
    {
      "neighborhood": "F-6",
      "listingCount": 3,
      "mappedCount": 3,
      "outlierCount": 0,
      "medianPricePkr": 550000000.0,
      "medianPricePerSqft": 61111.11,
      "medianPricePerMarla": 13750000.0
    },
    {
      "neighborhood": "E-7",
      "listingCount": 1,
      "mappedCount": 1,
      "outlierCount": 0,
      "medianPricePkr": 550000000.0,
      "medianPricePerSqft": 61111.11,
      "medianPricePerMarla": 13750000.0
    },
    {
      "neighborhood": "F-8",
      "listingCount": 10,
      "mappedCount": 10,
      "outlierCount": 0,
      "medianPricePkr": 270000000.0,
      "medianPricePerSqft": 56165.36,
      "medianPricePerMarla": 12637206.66
    },
    {
      "neighborhood": "I-10",
      "listingCount": 1,
      "mappedCount": 1,
      "outlierCount": 0,
      "medianPricePkr": 57000000.0,
      "medianPricePerSqft": 50666.67,
      "medianPricePerMarla": 11400000.0
    },
    {
      "neighborhood": "F-7",
      "listingCount": 3,
      "mappedCount": 3,
      "outlierCount": 0,
      "medianPricePkr": 550000000.0,
      "medianPricePerSqft": 49572.65,
      "medianPricePerMarla": 11153846.15
    },
    {
      "neighborhood": "G-9/4",
      "listingCount": 1,
      "mappedCount": 0,
      "outlierCount": 0,
      "medianPricePkr": 80000000.0,
      "medianPricePerSqft": 46176.05,
      "medianPricePerMarla": 10389610.39
    },
    {
      "neighborhood": "Blue Area",
      "listingCount": 1,
      "mappedCount": 1,
      "outlierCount": 0,
      "medianPricePkr": 145000000.0,
      "medianPricePerSqft": 42120.55,
      "medianPricePerMarla": 9477124.18
    }
  ],
  "seedStats": [
    {
      "source": "zameen",
      "seed": "houses",
      "label": "Houses",
      "propertyGroup": "house",
      "enabled": true,
      "pagesScraped": 6,
      "pageCountDiscovered": 566,
      "listingCardsCollected": 150,
      "cacheHits": 0,
      "httpFailures": 0
    },
    {
      "source": "zameen",
      "seed": "houses-5-marla",
      "label": "Houses | 5 Marla",
      "propertyGroup": "house",
      "enabled": true,
      "pagesScraped": 6,
      "pageCountDiscovered": 64,
      "listingCardsCollected": 150,
      "cacheHits": 0,
      "httpFailures": 0
    },
    {
      "source": "zameen",
      "seed": "houses-10-marla",
      "label": "Houses | 10 Marla",
      "propertyGroup": "house",
      "enabled": true,
      "pagesScraped": 6,
      "pageCountDiscovered": 64,
      "listingCardsCollected": 150,
      "cacheHits": 0,
      "httpFailures": 0
    },
    {
      "source": "zameen",
      "seed": "houses-1-kanal",
      "label": "Houses | 1 Kanal",
      "propertyGroup": "house",
      "enabled": true,
      "pagesScraped": 6,
      "pageCountDiscovered": 64,
      "listingCardsCollected": 150,
      "cacheHits": 0,
      "httpFailures": 0
    },
    {
      "source": "zameen",
      "seed": "apartments",
      "label": "Flats & Apartments",
      "propertyGroup": "apartment",
      "enabled": true,
      "pagesScraped": 6,
      "pageCountDiscovered": 165,
      "listingCardsCollected": 149,
      "cacheHits": 0,
      "httpFailures": 0
    },
    {
      "source": "zameen",
      "seed": "plots",
      "label": "Residential Plots",
      "propertyGroup": "plot",
      "enabled": true,
      "pagesScraped": 6,
      "pageCountDiscovered": 1114,
      "listingCardsCollected": 150,
      "cacheHits": 0,
      "httpFailures": 0
    },
    {
      "source": "zameen",
      "seed": "plots-5-marla",
      "label": "Residential Plots | 5 Marla",
      "propertyGroup": "plot",
      "enabled": true,
      "pagesScraped": 6,
      "pageCountDiscovered": 1114,
      "listingCardsCollected": 150,
      "cacheHits": 0,
      "httpFailures": 0
    },
    {
      "source": "zameen",
      "seed": "plots-10-marla",
      "label": "Residential Plots | 10 Marla",
      "propertyGroup": "plot",
      "enabled": true,
      "pagesScraped": 6,
      "pageCountDiscovered": 1114,
      "listingCardsCollected": 150,
      "cacheHits": 0,
      "httpFailures": 0
    },
    {
      "source": "zameen",
      "seed": "plots-1-kanal",
      "label": "Residential Plots | 1 Kanal",
      "propertyGroup": "plot",
      "enabled": true,
      "pagesScraped": 6,
      "pageCountDiscovered": 1114,
      "listingCardsCollected": 150,
      "cacheHits": 0,
      "httpFailures": 0
    },
    {
      "source": "graana",
      "seed": "graana-houses",
      "label": "Graana Houses",
      "propertyGroup": "house",
      "enabled": true,
      "pagesScraped": 2,
      "pageCountDiscovered": 2,
      "listingCardsCollected": 30,
      "cacheHits": 0,
      "httpFailures": 0
    },
    {
      "source": "graana",
      "seed": "graana-apartments",
      "label": "Graana Flats & Apartments",
      "propertyGroup": "apartment",
      "enabled": true,
      "pagesScraped": 2,
      "pageCountDiscovered": 2,
      "listingCardsCollected": 30,
      "cacheHits": 0,
      "httpFailures": 0
    },
    {
      "source": "graana",
      "seed": "graana-plots",
      "label": "Graana Residential Plots",
      "propertyGroup": "plot",
      "enabled": true,
      "pagesScraped": 2,
      "pageCountDiscovered": 2,
      "listingCardsCollected": 30,
      "cacheHits": 0,
      "httpFailures": 0
    }
  ],
  "fbrReference": {
    "label": "FBR Islamabad immovable property valuation",
    "url": "https://www.fbr.gov.pk/propertyValuation/17653",
    "documentUrl": "https://download1.fbr.gov.pk/SROs/2026416174174449SRO644.pdf",
    "note": "Official valuation reference. Numeric matching is shown only when an area table is mapped."
  }
}